altifier/__init__.py
altifier-0.1.0.dist-info/METADATA
altifier-0.1.0.dist-info/WHEEL
altifier-0.1.0.dist-info/top_level.txt
altifier-0.1.0.dist-info/RECORD
