Metadata-Version: 2.1
Name: altifier
Version: 0.1.0
Summary: library to convert text to alty text
Home-page: https://github.com/sirscripter/altifier
Author: restriction policy happend
Author-email: zaksteryt@gmail.com
Classifier: Programming Language :: Python :: 3
Classifier: License :: OSI Approved :: MIT License
Classifier: Operating System :: OS Independent
Requires-Python: >=3.6
